LICENSE
MANIFEST.in
README.rst
setup.py
django_starcross_gallery.egg-info/PKG-INFO
django_starcross_gallery.egg-info/SOURCES.txt
django_starcross_gallery.egg-info/dependency_links.txt
django_starcross_gallery.egg-info/requires.txt
django_starcross_gallery.egg-info/top_level.txt
gallery/__init__.py
gallery/admin.py
gallery/apps.py
gallery/forms.py
gallery/models.py
gallery/runtests.py
gallery/settings.py
gallery/signals.py
gallery/urls.py
gallery/views.py
gallery/static/gallery/css/gallery.css
gallery/static/gallery/css/gallery_template.css
gallery/static/gallery/css/themes/black.css
gallery/static/gallery/css/themes/grey.css
gallery/static/gallery/css/themes/white.css
gallery/static/gallery/images/35mm.png
gallery/static/gallery/images/album.png
gallery/static/gallery/images/aperture.png
gallery/static/gallery/images/calendar.png
gallery/static/gallery/images/camera.png
gallery/static/gallery/images/exposure.png
gallery/static/gallery/images/iso.png
gallery/static/gallery/images/lens.png
gallery/static/gallery/images/starcross.png
gallery/static/gallery/js/image_navigation.js
gallery/static/gallery/js/image_upload.js
gallery/static/gallery/js/infinite_scroll.js
gallery/static/gallery/js/justify_images.js
gallery/templates/gallery/album_detail.html
gallery/templates/gallery/album_list.html
gallery/templates/gallery/gallery_base.html
gallery/templates/gallery/image_detail.html
gallery/templates/gallery/image_list.html
gallery/templates/gallery/image_upload.html
gallery/templates/gallery/admin/thumbnail.html
gallery/templates/gallery/partials/image_upload_form.html
gallery/templates/gallery/partials/justify_images.html
gallery/templates/gallery/partials/thumbnail.html
gallery/templates/gallery/partials/thumbnail_empty.html
gallery/templates/gallery/partials/thumbnail_preview.html
gallery/tests/__init__.py
gallery/tests/test_settings.py
gallery/tests/tests.py
gallery/tests/urls.py