Metadata-Version: 2.1
Name: django-starcross-gallery
Version: 1.1.1
Summary: A streamlined Django gallery app with justified layout, infinite scrolling, and drag & drop uploading
Home-page: https://starcross.dev
Author: Alex Luton
Author-email: gallery@starcross.dev
License: GNU LGPLv3
Classifier: Development Status :: 5 - Production/Stable
Classifier: Environment :: Web Environment
Classifier: Framework :: Django
Classifier: Intended Audience :: Developers
Classifier: License :: OSI Approved :: GNU Lesser General Public License v3 (LGPLv3)
Classifier: Operating System :: OS Independent
Classifier: Programming Language :: Python
Classifier: Programming Language :: Python :: 3.8
Classifier: Programming Language :: Python :: 3.9
Classifier: Programming Language :: Python :: 3.10
Classifier: Programming Language :: Python :: 3.11
Classifier: Programming Language :: Python :: 3.12
Classifier: Topic :: Internet :: WWW/HTTP
Classifier: Topic :: Internet :: WWW/HTTP :: Dynamic Content
License-File: LICENSE
Requires-Dist: django-imagekit
Requires-Dist: Pillow
